pylint_json2checkstyle/__init__.py
pylint_json2checkstyle/checkstyle_reporter.py
pylint_json2checkstyle-0.0.13.dist-info/LICENSE
pylint_json2checkstyle-0.0.13.dist-info/METADATA
pylint_json2checkstyle-0.0.13.dist-info/WHEEL
pylint_json2checkstyle-0.0.13.dist-info/entry_points.txt
pylint_json2checkstyle-0.0.13.dist-info/top_level.txt
pylint_json2checkstyle-0.0.13.dist-info/RECORD
