Metadata-Version: 2.1
Name: pylint_json2checkstyle
Version: 0.0.13
Summary: A Pylint plugin and command line tool to produce Pylint reports in checkstyle format.
Home-page: https://github.com/caarmen/pylint-json2checkstyle
Author: Carmen Alvarez
Author-email: carmen@rmen.ca
Project-URL: Bug Tracker, https://github.com/caarmen/pylint-json2checkstyle/issues
Project-URL: Releases, https://github.com/caarmen/pylint-json2checkstyle/releases
Classifier: Development Status :: 3 - Alpha
Classifier: Environment :: Console
Classifier: Intended Audience :: Developers
Classifier: License :: OSI Approved :: MIT License
Classifier: Operating System :: OS Independent
Classifier: Programming Language :: Python :: 3
Classifier: Programming Language :: Python :: 3 :: Only
Classifier: Programming Language :: Python :: 3.6
Classifier: Programming Language :: Python :: 3.7
Classifier: Programming Language :: Python :: 3.8
Classifier: Programming Language :: Python :: 3.9
Classifier: Programming Language :: Python :: 3.10
Classifier: Programming Language :: Python :: 3.11
Classifier: Programming Language :: Python :: 3.12
Requires-Python: >=3.6
License-File: LICENSE
Requires-Dist: pylint
